pyinterview/__init__.py
pyinterview/graphs.py
pyinterview/heaps.py
pyinterview/linked_lists.py
pyinterview/searching.py
pyinterview/sorting.py
pyinterview/trees.py
pyinterview/tries.py
pyinterview-0.1.5.dist-info/LICENSE
pyinterview-0.1.5.dist-info/METADATA
pyinterview-0.1.5.dist-info/WHEEL
pyinterview-0.1.5.dist-info/top_level.txt
pyinterview-0.1.5.dist-info/RECORD
